kiettruong/__init__.py
kiettruong/kiettruong.py
kiettruong-0.1.0.dist-info/METADATA
kiettruong-0.1.0.dist-info/WHEEL
kiettruong-0.1.0.dist-info/RECORD
