Metadata-Version: 2.4
Name: kiettruong
Version: 0.1.0
Summary: 
Author: Truong Anh Kiet
Author-email: truonganhkiet291006@gmail.com
Requires-Python: >=3.13
Classifier: Programming Language :: Python :: 3
Classifier: Programming Language :: Python :: 3.13
Classifier: Programming Language :: Python :: 3.14
Requires-Dist: pandas (>=2.3.3,<3.0.0)
